napari_hub_cli/__init__.py
napari_hub_cli/_version.py
napari_hub_cli/cli.py
napari_hub_cli/constants.py
napari_hub_cli/formatting.py
napari_hub_cli/meta_classes.py
napari_hub_cli/napari_hub_cli.py
napari_hub_cli/utils.py
napari_hub_cli/_tests/__init__.py
napari_hub_cli/_tests/config_enum.py
napari_hub_cli/_tests/conftest.py
napari_hub_cli/_tests/test_missing_meta.py
napari_hub_cli/_tests/test_preview_meta.py
napari_hub_cli/_tests/resources/README.md
napari_hub_cli/_tests/resources/VERSION
napari_hub_cli/_tests/resources/setup.cfg
napari_hub_cli/_tests/resources/setup.py
napari_hub_cli/_tests/resources/.napari/DESCRIPTION.md
napari_hub_cli/_tests/resources/.napari/config.yml
napari_hub_cli/_tests/resources/test_plugin_name/__init__.py
napari_hub_cli/_tests/resources/test_plugin_name/_version.py
napari_hub_cli/resources/metadata_sources.csv
napari_hub_cli/resources/metadata_usage.csv
napari_hub_cli-0.0.4.dist-info/LICENSE
napari_hub_cli-0.0.4.dist-info/METADATA
napari_hub_cli-0.0.4.dist-info/WHEEL
napari_hub_cli-0.0.4.dist-info/entry_points.txt
napari_hub_cli-0.0.4.dist-info/top_level.txt
napari_hub_cli-0.0.4.dist-info/RECORD
