Metadata-Version: 2.1
Name: napari-hub-cli
Version: 0.0.4
Summary: Command line utilities for inspecting and validating plugins for the napari hub
Home-page: https://github.com/chanzuckerberg/napari-hub-cli
Author: CZI Imaging
Author-email: team@napari.dev
License: MIT
Platform: UNKNOWN
Classifier: Development Status :: 2 - Pre-Alpha
Classifier: Intended Audience :: Developers
Classifier: License :: OSI Approved :: BSD License
Classifier: Natural Language :: English
Classifier: Programming Language :: Python :: 3
Classifier: Programming Language :: Python :: 3.6
Classifier: Programming Language :: Python :: 3.7
Classifier: Programming Language :: Python :: 3.8
Requires-Python: >=3.6
License-File: LICENSE
Requires-Dist: numpy
Requires-Dist: pandas
Requires-Dist: parsesetup
Requires-Dist: PyYAML
